README.md
setup.py
CLUIE/CLUIE.py
CLUIE/__init__.py
CLUIE/models.py
CLUIE/view_generator.py
CLUIE.egg-info/PKG-INFO
CLUIE.egg-info/SOURCES.txt
CLUIE.egg-info/dependency_links.txt
CLUIE.egg-info/not-zip-safe
CLUIE.egg-info/requires.txt
CLUIE.egg-info/top_level.txt